[
    {
        "lat": 42.3324485, 
        "lon": -71.0502683
    }, 
    {
        "lat": 42.33865120000001, 
        "lon": -71.1077724
    }, 
    {
        "lat": 42.29077399999999, 
        "lon": -71.044713
    }, 
    {
        "lat": 42.333626, 
        "lon": -71.04042299999999
    }, 
    {
        "lat": 42.3209058, 
        "lon": -71.1068181
    }, 
    {
        "lat": 42.3078499, 
        "lon": -71.1145289
    }, 
    {
        "lat": 42.3227017, 
        "lon": -71.0619342
    }, 
    {
        "lat": 42.2886442, 
        "lon": -71.0511762
    }, 
    {
        "lat": 42.3315632, 
        "lon": -71.11889719999999
    }, 
    {
        "lat": 42.327545, 
        "lon": -71.070133
    }, 
    {
        "lat": 42.316854, 
        "lon": -71.099637
    }, 
    {
        "lat": 42.3066249, 
        "lon": -71.058331
    }, 
    {
        "lat": 42.29671460000001, 
        "lon": -71.0527482
    }, 
    {
        "lat": 42.29852470000001, 
        "lon": -71.05699539999999
    }, 
    {
        "lat": 42.3248444, 
        "lon": -71.0641552
    }, 
    {
        "lat": 42.30454789999999, 
        "lon": -71.1079589
    }, 
    {
        "lat": 42.323588, 
        "lon": -71.053933
    }, 
    {
        "lat": 42.3354949, 
        "lon": -71.0580385
    }, 
    {
        "lat": 42.3292603, 
        "lon": -71.07084499999999
    }, 
    {
        "lat": 42.3204292, 
        "lon": -71.10926719999999
    }, 
    {
        "lat": 42.3335882, 
        "lon": -71.0539635
    }, 
    {
        "lat": 42.33197099999999, 
        "lon": -71.071606
    }, 
    {
        "lat": 42.293862, 
        "lon": -71.06848099999999
    }
]